alteruphono/__init__.py
alteruphono/__main__.py
alteruphono/ast.py
alteruphono/changer.py
alteruphono/globals.py
alteruphono/model.py
alteruphono/parser.py
alteruphono/rule.py
alteruphono/sequence.py
alteruphono/utils.py
alteruphono/parser/__init__.py
alteruphono/parser/parser.py
alteruphono/parser/sound_change.ebnf
resources/classes.tsv
resources/features.tsv
resources/features_bipa.tsv
resources/sound_changes.tsv
resources/sound_classes.tsv
resources/sounds.tsv
resources/model_default/classes.tsv
resources/model_default/features.tsv
resources/model_default/sounds.tsv
tests/__init__.py
tests/test_changers.py
tests/test_parser.py
alteruphono-0.4.dist-info/AUTHORS.md
alteruphono-0.4.dist-info/LICENSE
alteruphono-0.4.dist-info/METADATA
alteruphono-0.4.dist-info/WHEEL
alteruphono-0.4.dist-info/entry_points.txt
alteruphono-0.4.dist-info/top_level.txt
alteruphono-0.4.dist-info/RECORD
