Metadata-Version: 2.1
Name: alteruphono
Version: 0.4
Summary: Library for dealing with sound changes
Home-page: https://github.com/tresoldi/alteruphono
Author: Tiago Tresoldi
Author-email: tresoldi@shh.mpg.de
License: MIT
Keywords: sound change,phonology,phonetics,Lautwandel
Platform: UNKNOWN
Classifier: License :: OSI Approved :: MIT License
Classifier: Operating System :: OS Independent
Classifier: Programming Language :: Python :: 3
Classifier: Topic :: Software Development :: Libraries
Requires-Dist: arpeggio
